dml_util/__about__.py
dml_util/__init__.py
dml_util/funk.py
dml_util/wrapper.py
dml_util/adapters/__init__.py
dml_util/adapters/base.py
dml_util/adapters/lambda_.py
dml_util/adapters/local.py
dml_util/aws/__init__.py
dml_util/aws/dynamodb.py
dml_util/aws/s3.py
dml_util/core/__init__.py
dml_util/core/config.py
dml_util/core/state.py
dml_util/core/utils.py
dml_util/dags/__init__.py
dml_util/dags/batch/__init__.py
dml_util/dags/batch/cf.json
dml_util/dags/batch/impl.py
dml_util/dags/ecr/__init__.py
dml_util/dags/ecr/cf.json
dml_util/experimental/__init__.py
dml_util/experimental/api.py
dml_util/lib/__init__.py
dml_util/lib/dkr.py
dml_util/lib/submit.py
dml_util/runners/__init__.py
dml_util/runners/base.py
dml_util/runners/batch.py
dml_util/runners/cloudformation.py
dml_util/runners/container.py
dml_util/runners/lambda_.py
dml_util/runners/local.py
dml_util/runners/remote.py
dml_util-0.0.21.post2.dist-info/METADATA
dml_util-0.0.21.post2.dist-info/WHEEL
dml_util-0.0.21.post2.dist-info/entry_points.txt
dml_util-0.0.21.post2.dist-info/licenses/LICENSE.txt
dml_util-0.0.21.post2.dist-info/RECORD
