Metadata-Version: 2.4
Name: dml-util
Version: 0.0.21.post2
Project-URL: Documentation, https://github.com/daggerml/dml-util#readme
Project-URL: Issues, https://github.com/daggerml/dml-util/issues
Project-URL: Source, https://github.com/daggerml/dml-util
Author-email: Aaron Niskin <aaron@niskin.org>
License-Expression: MIT
License-File: LICENSE.txt
Classifier: Development Status :: 4 - Beta
Classifier: Programming Language :: Python
Classifier: Programming Language :: Python :: 3
Classifier: Programming Language :: Python :: 3.9
Classifier: Programming Language :: Python :: 3.10
Classifier: Programming Language :: Python :: 3.11
Classifier: Programming Language :: Python :: 3.12
Classifier: Programming Language :: Python :: 3.13
Classifier: Programming Language :: Python :: Implementation :: CPython
Classifier: Programming Language :: Python :: Implementation :: PyPy
Requires-Python: >=3.9
Requires-Dist: boto3
Requires-Dist: daggerml==0.0.38.post2
Provides-Extra: dev
Requires-Dist: moto[all,server]; extra == 'dev'
Requires-Dist: pytest; extra == 'dev'
Requires-Dist: pytest-cov; extra == 'dev'
Provides-Extra: dml
Requires-Dist: daggerml-cli==0.0.38.post1; extra == 'dml'
Requires-Dist: watchtower; extra == 'dml'
Provides-Extra: nb
Requires-Dist: jupyter; extra == 'nb'
Requires-Dist: nbconvert; extra == 'nb'
